asifjamali/__init__.py
asifjamali/musibat.py
asifjamali-30.0.1.dist-info/LICENSE
asifjamali-30.0.1.dist-info/METADATA
asifjamali-30.0.1.dist-info/WHEEL
asifjamali-30.0.1.dist-info/top_level.txt
asifjamali-30.0.1.dist-info/RECORD
