Metadata-Version: 2.1
Name: asifjamali
Version: 30.0.1
Summary: Team Musibat Bots
Home-page: https://bitbucket.org/shahzain83/musibat
Author: Shahzain Khan
Author-email: technomusibat@hotmail.com
License: MIT
Project-URL: Bug Tracker, https://bitbucket.org/shahzain83/musibat/issues
License-File: LICENSE
Requires-Dist: requests
